{
  "Test1": {
    "name": "Test1",
    "students": [
      {
        "name": "Sophia Davis",
        "score": 92,
        "sex": "F"
      },
      {
        "name": "Noah Wilson",
        "score": 81,
        "sex": "M"
      },
      {
        "name": "Ava Anderson",
        "score": 95,
        "sex": "F"
      },
      {
        "name": "Mason Thomas",
        "score": 69,
        "sex": "M"
      },
      {
        "name": "Isabella Taylor",
        "score": 84,
        "sex": "F"
      },
      {
        "name": "Ethan Moore",
        "score": 78,
        "sex": "M"
      },
      {
        "name": "Mia Jackson",
        "score": 91,
        "sex": "F"
      },
      {
        "name": "Logan White",
        "score": 73,
        "sex": "M"
      },
      {
        "name": "Olivia Harris",
        "score": 89,
        "sex": "F"
      },
      {
        "name": "Lucas Martin",
        "score": 80,
        "sex": "M"
      },
      {
        "name": "Chloe Lewis",
        "score": 93,
        "sex": "F"
      },
      {
        "name": "Jacob Walker",
        "score": 77,
        "sex": "M"
      },
      {
        "name": "Madison Hall",
        "score": 85,
        "sex": "F"
      }
    ],
    "created": "2025-06-03T00:31:57.760Z"
  },
  "Test2": {
    "name": "Test2",
    "students": [
      {
        "name": "Avery Young",
        "score": 86,
        "sex": "F"
      },
      {
        "name": "Caleb King",
        "score": 74,
        "sex": "M"
      },
      {
        "name": "Harper Wright",
        "score": 90,
        "sex": "F"
      },
      {
        "name": "William Scott",
        "score": 79,
        "sex": "M"
      },
      {
        "name": "Ella Green",
        "score": 94,
        "sex": "F"
      },
      {
        "name": "Benjamin Adams",
        "score": 68,
        "sex": "M"
      },
      {
        "name": "Abigail Baker",
        "score": 82,
        "sex": "F"
      },
      {
        "name": "Henry Nelson",
        "score": 75,
        "sex": "M"
      },
      {
        "name": "Lily Carter",
        "score": 87,
        "sex": "F"
      },
      {
        "name": "Samuel Mitchell",
        "score": 72,
        "sex": "M"
      },
      {
        "name": "Grace Perez",
        "score": 91,
        "sex": "F"
      },
      {
        "name": "Owen Roberts",
        "score": 83,
        "sex": "M"
      },
      {
        "name": "Zoe Turner",
        "score": 88,
        "sex": "F"
      },
      {
        "name": "Jackson Phillips",
        "score": 70,
        "sex": "M"
      },
      {
        "name": "Victoria Campbell",
        "score": 93,
        "sex": "F"
      },
      {
        "name": "Daniel Parker",
        "score": 77,
        "sex": "M"
      },
      {
        "name": "Natalie Evans",
        "score": 85,
        "sex": "F"
      },
      {
        "name": "Andrew Edwards",
        "score": 80,
        "sex": "M"
      },
      {
        "name": "Brooklyn Collins",
        "score": 89,
        "sex": "F"
      },
      {
        "name": "Ryan Stewart",
        "score": 76,
        "sex": "M"
      }
    ],
    "created": "2025-06-03T00:33:05.192Z"
  }
}